us_netview/Lace.py
us_netview/Netview_excel.py
us_netview/SLDUE.py
us_netview/__init__.py
us_netview/any_wings.py
us_netview/avg4lac.py
us_netview/moapmmvrem.py
us_netview/mosumwts.py
us_netview/netview_xlwings_version.py
us_netview/remwts.py
us_netview/sumwts.py
us_netview/tgb2.py
us_netview/tgb2_1month.py
us_netview/total.py
us_netview/us_netview_non_major.py
us_netview/uscontrols.py
us_netview/Templates/HomeInternetUE_Calcs.xlsx
us_netview/Templates/Procedures for Computing Spanish Language UEs.xlsx
us_netview/Templates/e_NNR_HomeUEs.xlsx
us_netview/Templates/e_Persons2+.xlsx
us_netview_non_major-0.9.data/scripts/us_netview_non_major
us_netview_non_major-0.9.data/scripts/us_netview_non_major.py
us_netview_non_major-0.9.dist-info/LICENSE
us_netview_non_major-0.9.dist-info/METADATA
us_netview_non_major-0.9.dist-info/WHEEL
us_netview_non_major-0.9.dist-info/top_level.txt
us_netview_non_major-0.9.dist-info/RECORD
